lockfale_connectors/__init__.py
lockfale_connectors/lf_kafka/__init__.py
lockfale_connectors/lf_kafka/kafka_consumer.py
lockfale_connectors/lf_kafka/kafka_producer.py
lockfale_connectors/lf_kafka/schemas/__init__.py
lockfale_connectors/lf_kafka/schemas/base.py
lockfale_connectors/lf_kafka/schemas/cyberpartner.py
lockfale_connectors/lf_kafka/schemas/topics.py
lockfale_connectors/mqtt/__init__.py
lockfale_connectors/mqtt/mqtt_client.py
lockfale_connectors/mqtt/mqtt_handlers.py
lockfale_connectors/mqtt/mqtt_publisher.py
lockfale_connectors/mqtt/mqtt_subscriber.py
lockfale_connectors/postgres/__init__.py
lockfale_connectors/postgres/config.py
lockfale_connectors/postgres/pgsql.py
lockfale_connectors-1.5.0.dist-info/METADATA
lockfale_connectors-1.5.0.dist-info/WHEEL
lockfale_connectors-1.5.0.dist-info/RECORD
