Metadata-Version: 2.3
Name: lockfale-connectors
Version: 1.5.0
Summary: Connectors for Kafka, MQTT, and PostgreSQL. These connectors are specifically for use in the Cyberpartner applications.
License: MIT
Author: Alex Persinger
Author-email: nutcrunch@cackalackycon.org
Requires-Python: >=3.12,<4.0
Classifier: License :: OSI Approved :: MIT License
Classifier: Programming Language :: Python :: 3
Classifier: Programming Language :: Python :: 3.12
Classifier: Programming Language :: Python :: 3.13
Requires-Dist: jsonschema
Requires-Dist: kafka-python
Requires-Dist: paho-mqtt (>=2.1,<2.2)
Requires-Dist: pandas (==2.2)
Requires-Dist: psycopg[binary] (>=3.2,<3.3)
Requires-Dist: pydantic
Requires-Dist: pydantic-settings
